{"categoryGeneratedIndex":{"title":"Compute","description":"Instances are computing units that provide you with resources to run your applications/workloads. Linux Instances are virtual machines that run the images of Linux Operating Systems, for example, Ubuntu, CentOS, Rocky, Oracle, Debian, etc. ","slug":"/category/compute","permalink":"/docs/category/compute","sidebar":"sidebar1","navigation":{"previous":{"title":"Standard Agreements","permalink":"/docs/Subscribers/AccountCentre/StandardAgreements"},"next":{"title":"Kubernetes","permalink":"/docs/category/kubernetes"}}}}